{"status": "succeeded", "createdDateTime": "2023-04-13T15:11:54Z", "lastUpdatedDateTime": "2023-04-13T15:11:57Z", "analyzeResult": {"apiVersion": "2022-08-31", "modelId": "prebuilt-layout", "stringIndexType": "utf16CodeUnit", "content": "Arc File\nEdit View\nSpaces\nTabs\nArchive Extensions\nWindow\nHelp\nUS\nThu Apr 13 11:11 AM\nRegister now >\nPortal\nMicrosoft Build\nMay 23-25, 2023\nMicrosoft\nLearn\nDocumentation\n...\n\u00d7\nTraining Certifications Q&A Code Samples Assessments\nShows\nEvents\nSearch\nSign in\nAzure Product documentation v Architecture v Learn Azure v Develop v Resources v\nVersion\nForm Recognizer v3.0 V\nFilter by title\nFree account\nLearn / Azure / Applied Al Services / Form Recognizer /\n+ ...\nAzure Form Recognizer layout model\nAnalyze document API response Read OCR model\nGeneral document model\nLayout model\nNEW Query field extraction (preview)\nNEW Health insurance card model\nNEW Add-on capabilities (preview)\nW-2 form model\nInvoice model\nReceipt model\nID document model\nBusiness card model\n> Custom models\n> Tutorials\n> Reference\n> Resources\nArticle \u00b7 03/12/2023 \u00b7 9 contributors\n& Feedback\nIn this article\nDocument layout analysis\nDevelopment options\nInput requirements\nForm Recognizer Studio\nShow 4 more\nThis article applies to: 1 Form Recognizer v3.0. Earlier version: Form Recognizer v2.1\nForm Recognizer layout model is an advanced machine-learning based document analysis API available in the Form Recognizer cloud. It enables you to take documents in various formats and return structured data representations of the documents. It combines an enhanced version of our powerful Optical Character Recognition (OCR) capabilities with deep learning models to extract text, tables, selection marks, and document structure.\nDocument layout analysis\nDocument structure layout analysis is the process of analyzing a document to extract regions of interact and their intAr malatiAnchine The Anal is to Avtract tout and structural AlAmante from the\nEl Download PDF :unselected: :unselected: :unselected: :selected:", "pages": [{"angle": 0.07161957770586014, "width": 3024, "height": 1964, "unit": "pixel", "words": [{"content": "Arc", "polygon": [105, 24, 149, 23, 49, 48], "confidence": 0.992, "span": {"offset": 0, "length": 3}}, {"content": "File", "polygon": [188, 23, 234, 49, 50], "confidence": 0.988, "span": {"offset": 4, "length": 4}}, {"content": "Edit", "polygon": [271, 22, 328, 21, 329, 52], "confidence": 0.988, "span": {"offset": 9, "length": 4}}, {"content": "View", "polygon": [360, 22, 415, 23, 416, 52, 361, 51], "confidence": 0.987, "span": {"offset": 14, "length": 4}}, {"content": "Spaces", "polygon": [460, 23, 553, 24, 53, 51], "confidence": 0.997, "span": {"offset": 19, "length": 6}}, {"content": "Tabs", "polygon": [593, 22, 652, 50], "confidence": 0.985, "span": {"offset": 26, "length": 4}}, {"content": "Archive", "polygon": [689, 24, 782, 781, 50, 688], "confidence": 0.996, "span": {"offset": 31, "length": 7}}, {"content": "Extensions", "polygon": [820, 24, 955, 956, 51, 50], "confidence": 0.993, "span": {"offset": 39, "length": 10}}, {"content": "Window", "polygon": [992, 22, 1086, 23, 1085, 50, 49], "confidence": 0.997, "span": {"offset": 50, "length": 6}}, {"content": "Help", "polygon": [1130, 24, 1187, 25, 1186, 52, 1129, 51], "confidence": 0.987, "span": {"offset": 57, "length": 4}}, {"content": "US", "polygon": [2294, 24, 2326, 47, 46], "confidence": 0.996, "span": {"offset": 62, "length": 2}}, {"content": "Thu", "polygon": [2720, 21, 2764, 22, 2765, 50, 51], "confidence": 0.993, "span": {"offset": 65, "length": 3}}, {"content": "Apr", "polygon": [2772, 22, 2819, 23, 50], "confidence": 0.998, "span": {"offset": 69, "length": 3}}, {"content": "13", "polygon": [2825, 23, 2855, 50], "confidence": 0.997, "span": {"offset": 73, "length": 2}}, {"content": "11:11", "polygon": [2871, 23, 2944, 2943, 50], "confidence": 0.997, "span": {"offset": 76, "length": 5}}, {"content": "AM", "polygon": [2949, 23, 2983, 50], "confidence": 0.997, "span": {"offset": 82, "length": 2}}, {"content": "Register", "polygon": [739, 207, 858, 208, 242, 738, 241], "confidence": 0.991, "span": {"offset": 85, "length": 8}}, {"content": "now", "polygon": [864, 208, 921, 207, 922, 240, 865, 242], "confidence": 0.998, "span": {"offset": 94, "length": 3}}, {"content": ">", "polygon": [943, 207, 961, 206, 962, 237, 944, 238], "confidence": 0.847, "span": {"offset": 98, "length": 1}}, {"content": "Portal", "polygon": [2616, 517, 2697, 518, 546, 545], "confidence": 0.997, "span": {"offset": 100, "length": 6}}, {"content": "Microsoft", "polygon": [54, 154, 347, 151, 214, 53, 213], "confidence": 0.993, "span": {"offset": 107, "length": 9}}, {"content": "Build", "polygon": [360, 151, 518, 214, 359], "confidence": 0.991, "span": {"offset": 117, "length": 5}}, {"content": "May", "polygon": [52, 262, 103, 261, 102, 293, 51], "confidence": 0.991, "span": {"offset": 123, "length": 3}}, {"content": "23-25,", "polygon": [109, 261, 189, 293, 108], "confidence": 0.996, "span": {"offset": 127, "length": 6}}, {"content": "2023", "polygon": [195, 261, 258, 262, 257, 291, 293], "confidence": 0.988, "span": {"offset": 134, "length": 4}}, {"content": "Microsoft", "polygon": [109, 406, 270, 405, 269, 441, 443], "confidence": 0.995, "span": {"offset": 139, "length": 9}}, {"content": "Learn", "polygon": [367, 410, 452, 411, 442, 366, 440], "confidence": 0.994, "span": {"offset": 149, "length": 5}}, {"content": "Documentation", "polygon": [504, 413, 695, 694, 440, 438], "confidence": 0.991, "span": {"offset": 155, "length": 13}}, {"content": "...", "polygon": [3019, 106, 3017, 136, 3006, 135, 3008], "confidence": 0.648, "span": {"offset": 169, "length": 3}}, {"content": "\u00d7", "polygon": [2899, 130, 2917, 131, 2915, 159, 2897, 158], "confidence": 0.709, "span": {"offset": 173, "length": 1}}, {"content": "Training", "polygon": [725, 412, 824, 411, 825, 441, 726], "confidence": 0.994, "span": {"offset": 175, "length": 8}}, {"content": "Certifications", "polygon": [854, 411, 1022, 442, 855], "confidence": 0.991, "span": {"offset": 184, "length": 14}}, {"content": "Q&A", "polygon": [1055, 411, 1117, 1118, 442, 1056], "confidence": 0.997, "span": {"offset": 199, "length": 3}}, {"content": "Code", "polygon": [1157, 411, 1223, 1224, 442], "confidence": 0.986, "span": {"offset": 203, "length": 4}}, {"content": "Samples", "polygon": [1229, 411, 1338, 412, 441, 1230, 442], "confidence": 0.993, "span": {"offset": 208, "length": 7}}, {"content": "Assessments", "polygon": [1366, 412, 1528, 413, 1527, 440, 441], "confidence": 0.992, "span": {"offset": 216, "length": 11}}, {"content": "Shows", "polygon": [1552, 412, 1637, 413, 439], "confidence": 0.997, "span": {"offset": 228, "length": 5}}, {"content": "Events", "polygon": [1664, 412, 1746, 413, 439, 438], "confidence": 0.997, "span": {"offset": 234, "length": 6}}, {"content": "Search", "polygon": [2466, 408, 2544, 410, 2543, 439, 2464], "confidence": 0.805, "span": {"offset": 241, "length": 6}}, {"content": "Sign", "polygon": [2832, 409, 2886, 410, 440, 439], "confidence": 0.988, "span": {"offset": 248, "length": 4}}, {"content": "in", "polygon": [2892, 410, 2918, 440], "confidence": 0.997, "span": {"offset": 253, "length": 2}}, {"content": "Azure", "polygon": [69, 519, 158, 157, 551, 68], "confidence": 0.993, "span": {"offset": 256, "length": 5}}, {"content": "Product", "polygon": [190, 519, 288, 520, 287, 550, 189, 551], "confidence": 0.996, "span": {"offset": 262, "length": 7}}, {"content": "documentation", "polygon": [294, 520, 485, 484, 550, 293], "confidence": 0.992, "span": {"offset": 270, "length": 13}}, {"content": "v", "polygon": [493, 520, 510, 521, 509, 550, 492], "confidence": 0.369, "span": {"offset": 284, "length": 1}}, {"content": "Architecture", "polygon": [547, 521, 701, 700, 549, 546, 550], "confidence": 0.96, "span": {"offset": 286, "length": 12}}, {"content": "v", "polygon": [707, 521, 724, 723, 549, 706], "confidence": 0.321, "span": {"offset": 299, "length": 1}}, {"content": "Learn", "polygon": [762, 521, 831, 830, 549, 760], "confidence": 0.955, "span": {"offset": 301, "length": 5}}, {"content": "Azure", "polygon": [837, 521, 912, 910, 549, 836], "confidence": 0.995, "span": {"offset": 307, "length": 5}}, {"content": "v", "polygon": [918, 521, 935, 933, 549, 917], "confidence": 0.403, "span": {"offset": 313, "length": 1}}, {"content": "Develop", "polygon": [972, 521, 1076, 1074, 549, 971], "confidence": 0.993, "span": {"offset": 315, "length": 7}}, {"content": "v", "polygon": [1084, 521, 1101, 1100, 549, 1083], "confidence": 0.338, "span": {"offset": 323, "length": 1}}, {"content": "Resources", "polygon": [1138, 521, 1267, 520, 1266, 549, 1137], "confidence": 0.978, "span": {"offset": 325, "length": 9}}, {"content": "v", "polygon": [1274, 520, 1290, 1289, 549, 1272], "confidence": 0.77, "span": {"offset": 335, "length": 1}}, {"content": "Version", "polygon": [51, 648, 154, 649, 152, 679, 678], "confidence": 0.996, "span": {"offset": 337, "length": 7}}, {"content": "Form", "polygon": [72, 716, 133, 715, 132, 758, 71, 759], "confidence": 0.988, "span": {"offset": 345, "length": 4}}, {"content": "Recognizer", "polygon": [142, 714, 285, 713, 284, 759, 141, 758], "confidence": 0.994, "span": {"offset": 350, "length": 10}}, {"content": "v3.0", "polygon": [293, 713, 347, 346, 759], "confidence": 0.964, "span": {"offset": 361, "length": 4}}, {"content": "V", "polygon": [667, 722, 679, 723, 678, 741, 666, 740], "confidence": 0.495, "span": {"offset": 366, "length": 1}}, {"content": "Filter", "polygon": [111, 798, 174, 799, 832, 112, 830], "confidence": 0.9, "span": {"offset": 368, "length": 6}}, {"content": "by", "polygon": [181, 799, 213, 212, 832], "confidence": 0.997, "span": {"offset": 375, "length": 2}}, {"content": "title", "polygon": [219, 799, 270, 800, 269, 832, 218], "confidence": 0.997, "span": {"offset": 378, "length": 5}}, {"content": "Free", "polygon": [2754, 519, 2808, 521, 2807, 548, 2752, 547], "confidence": 0.988, "span": {"offset": 384, "length": 4}}, {"content": "account", "polygon": [2816, 521, 2919, 520, 2918, 547, 2815, 548], "confidence": 0.996, "span": {"offset": 389, "length": 7}}, {"content": "Learn", "polygon": [794, 658, 865, 866, 689, 795, 688], "confidence": 0.993, "span": {"offset": 397, "length": 5}}, {"content": "/", "polygon": [875, 658, 894, 895, 689], "confidence": 0.994, "span": {"offset": 403, "length": 1}}, {"content": "Azure", "polygon": [901, 658, 979, 657, 980, 690, 902, 689], "confidence": 0.996, "span": {"offset": 405, "length": 5}}, {"content": "/", "polygon": [986, 657, 1006, 691, 987, 690], "confidence": 0.994, "span": {"offset": 411, "length": 1}}, {"content": "Applied", "polygon": [1013, 657, 1109, 1110, 691], "confidence": 0.993, "span": {"offset": 413, "length": 7}}, {"content": "Al", "polygon": [1116, 657, 1142, 1143, 691], "confidence": 0.681, "span": {"offset": 421, "length": 2}}, {"content": "Services", "polygon": [1149, 657, 1256, 692, 691], "confidence": 0.993, "span": {"offset": 424, "length": 8}}, {"content": "/", "polygon": [1263, 657, 1282, 692], "confidence": 0.995, "span": {"offset": 433, "length": 1}}, {"content": "Form", "polygon": [1289, 657, 1350, 692], "confidence": 0.991, "span": {"offset": 435, "length": 4}}, {"content": "Recognizer", "polygon": [1361, 657, 1504, 691, 1362, 692], "confidence": 0.993, "span": {"offset": 440, "length": 10}}, {"content": "/", "polygon": [1511, 657, 1529, 658, 691], "confidence": 0.994, "span": {"offset": 451, "length": 1}}, {"content": "+", "polygon": [2013, 661, 2026, 660, 2027, 679, 2014, 680], "confidence": 0.62, "span": {"offset": 453, "length": 1}}, {"content": "...", "polygon": [2165, 659, 681, 2152], "confidence": 0.847, "span": {"offset": 455, "length": 3}}, {"content": "Azure", "polygon": [798, 743, 1000, 814, 797, 803], "confidence": 0.997, "span": {"offset": 459, "length": 5}}, {"content": "Form", "polygon": [1022, 743, 1185, 821, 1021, 815], "confidence": 0.988, "span": {"offset": 465, "length": 4}}, {"content": "Recognizer", "polygon": [1231, 743, 1636, 742, 826, 822], "confidence": 0.995, "span": {"offset": 470, "length": 10}}, {"content": "layout", "polygon": [1651, 742, 1886, 822, 826], "confidence": 0.996, "span": {"offset": 481, "length": 6}}, {"content": "model", "polygon": [1901, 742, 2137, 741, 2138, 814, 822], "confidence": 0.997, "span": {"offset": 488, "length": 5}}, {"content": "Analyze", "polygon": [115, 900, 209, 899, 208, 931, 930], "confidence": 0.994, "span": {"offset": 494, "length": 7}}, {"content": "document", "polygon": [215, 899, 343, 342, 931, 214], "confidence": 0.996, "span": {"offset": 502, "length": 8}}, {"content": "API", "polygon": [349, 899, 392, 391, 931], "confidence": 0.918, "span": {"offset": 511, "length": 3}}, {"content": "response", "polygon": [398, 900, 514, 901, 513, 931, 397], "confidence": 0.995, "span": {"offset": 515, "length": 8}}, {"content": "Read", "polygon": [115, 958, 173, 986], "confidence": 0.991, "span": {"offset": 524, "length": 4}}, {"content": "OCR", "polygon": [181, 958, 236, 987, 986], "confidence": 0.997, "span": {"offset": 529, "length": 3}}, {"content": "model", "polygon": [244, 958, 325, 324, 987], "confidence": 0.997, "span": {"offset": 533, "length": 5}}, {"content": "General", "polygon": [118, 1018, 210, 209, 1046, 117, 1045], "confidence": 0.993, "span": {"offset": 539, "length": 7}}, {"content": "document", "polygon": [216, 1018, 343, 1017, 342, 1047, 215, 1046], "confidence": 0.993, "span": {"offset": 547, "length": 8}}, {"content": "model", "polygon": [348, 1017, 430, 1016, 1047], "confidence": 0.997, "span": {"offset": 556, "length": 5}}, {"content": "Layout", "polygon": [114, 1077, 199, 1076, 1108], "confidence": 0.995, "span": {"offset": 562, "length": 6}}, {"content": "model", "polygon": [205, 1076, 292, 1075, 291, 1107, 1108], "confidence": 0.997, "span": {"offset": 569, "length": 5}}, {"content": "NEW", "polygon": [118, 1141, 138, 1155, 1154], "confidence": 0.996, "span": {"offset": 575, "length": 3}}, {"content": "Query", "polygon": [152, 1135, 223, 1134, 1167, 151], "confidence": 0.993, "span": {"offset": 579, "length": 5}}, {"content": "field", "polygon": [230, 1134, 284, 283, 1167, 229], "confidence": 0.997, "span": {"offset": 585, "length": 5}}, {"content": "extraction", "polygon": [290, 1134, 416, 1168, 1167], "confidence": 0.994, "span": {"offset": 591, "length": 10}}, {"content": "(preview)", "polygon": [423, 1134, 539, 538, 1167, 422, 1168], "confidence": 0.993, "span": {"offset": 602, "length": 9}}, {"content": "NEW", "polygon": [121, 1199, 138, 1200, 137, 1213, 1212], "confidence": 0.955, "span": {"offset": 612, "length": 3}}, {"content": "Health", "polygon": [149, 1196, 229, 1195, 1225, 148, 1224], "confidence": 0.994, "span": {"offset": 616, "length": 6}}, {"content": "insurance", "polygon": [235, 1195, 355, 1226, 1225], "confidence": 0.995, "span": {"offset": 623, "length": 9}}, {"content": "card", "polygon": [361, 1194, 418, 1226], "confidence": 0.988, "span": {"offset": 633, "length": 4}}, {"content": "model", "polygon": [424, 1194, 508, 1193, 509, 1226, 425], "confidence": 0.997, "span": {"offset": 638, "length": 5}}, {"content": "NEW", "polygon": [118, 1259, 138, 1260, 1273, 117, 1272], "confidence": 0.992, "span": {"offset": 644, "length": 3}}, {"content": "Add-on", "polygon": [152, 1255, 242, 1254, 1286, 1284], "confidence": 0.997, "span": {"offset": 648, "length": 6}}, {"content": "capabilities", "polygon": [249, 1254, 390, 1253, 1286, 248], "confidence": 0.991, "span": {"offset": 655, "length": 12}}, {"content": "(preview)", "polygon": [397, 1253, 511, 1286, 396], "confidence": 0.994, "span": {"offset": 668, "length": 9}}, {"content": "W-2", "polygon": [116, 1312, 165, 1313, 166, 1342, 117, 1341], "confidence": 0.998, "span": {"offset": 678, "length": 3}}, {"content": "form", "polygon": [171, 1313, 223, 1314, 224, 1342], "confidence": 0.988, "span": {"offset": 682, "length": 4}}, {"content": "model", "polygon": [239, 1314, 321, 1313, 1343, 1342], "confidence": 0.997, "span": {"offset": 687, "length": 5}}, {"content": "Invoice", "polygon": [116, 1374, 200, 1400, 117], "confidence": 0.991, "span": {"offset": 693, "length": 7}}, {"content": "model", "polygon": [207, 1374, 291, 1373, 1400, 208], "confidence": 0.997, "span": {"offset": 701, "length": 5}}, {"content": "Receipt", "polygon": [117, 1432, 205, 1431, 1462, 118, 1461], "confidence": 0.996, "span": {"offset": 707, "length": 7}}, {"content": "model", "polygon": [211, 1431, 295, 294, 1462], "confidence": 0.997, "span": {"offset": 715, "length": 5}}, {"content": "ID", "polygon": [116, 1490, 138, 1519, 117], "confidence": 0.994, "span": {"offset": 721, "length": 2}}, {"content": "document", "polygon": [146, 1490, 276, 1519, 147], "confidence": 0.996, "span": {"offset": 724, "length": 8}}, {"content": "model", "polygon": [282, 1490, 365, 364, 1520, 1519], "confidence": 0.997, "span": {"offset": 733, "length": 5}}, {"content": "Business", "polygon": [117, 1551, 218, 1579, 1578], "confidence": 0.996, "span": {"offset": 739, "length": 8}}, {"content": "card", "polygon": [223, 1551, 280, 1579, 224], "confidence": 0.991, "span": {"offset": 748, "length": 4}}, {"content": "model", "polygon": [286, 1551, 365, 1550, 366, 1579], "confidence": 0.997, "span": {"offset": 753, "length": 5}}, {"content": ">", "polygon": [89, 1608, 105, 106, 1636, 90, 1635], "confidence": 0.68, "span": {"offset": 759, "length": 1}}, {"content": "Custom", "polygon": [111, 1608, 199, 1609, 1638, 112, 1636], "confidence": 0.997, "span": {"offset": 761, "length": 6}}, {"content": "models", "polygon": [215, 1609, 310, 309, 1638], "confidence": 0.997, "span": {"offset": 768, "length": 6}}, {"content": ">", "polygon": [57, 1669, 72, 1695, 1694], "confidence": 0.675, "span": {"offset": 775, "length": 1}}, {"content": "Tutorials", "polygon": [81, 1669, 188, 1670, 1697, 1695], "confidence": 0.994, "span": {"offset": 777, "length": 9}}, {"content": ">", "polygon": [58, 1728, 73, 1753], "confidence": 0.674, "span": {"offset": 787, "length": 1}}, {"content": "Reference", "polygon": [80, 1728, 204, 1730, 1756, 1754], "confidence": 0.995, "span": {"offset": 789, "length": 9}}, {"content": ">", "polygon": [58, 1787, 72, 1788, 1812, 1811], "confidence": 0.643, "span": {"offset": 799, "length": 1}}, {"content": "Resources", "polygon": [80, 1788, 208, 1790, 206, 1814, 1812], "confidence": 0.994, "span": {"offset": 801, "length": 9}}, {"content": "Article", "polygon": [796, 858, 878, 857, 890], "confidence": 0.991, "span": {"offset": 811, "length": 7}}, {"content": "\u00b7", "polygon": [884, 857, 897, 890], "confidence": 0.688, "span": {"offset": 819, "length": 1}}, {"content": "03/12/2023", "polygon": [903, 857, 1050, 858, 890], "confidence": 0.991, "span": {"offset": 821, "length": 10}}, {"content": "\u00b7", "polygon": [1059, 858, 1072, 890], "confidence": 0.526, "span": {"offset": 832, "length": 1}}, {"content": "9", "polygon": [1078, 858, 1095, 890], "confidence": 0.994, "span": {"offset": 834, "length": 1}}, {"content": "contributors", "polygon": [1102, 858, 1259, 860, 1258, 890, 1101], "confidence": 0.992, "span": {"offset": 836, "length": 12}}, {"content": "&", "polygon": [2021, 857, 2039, 887], "confidence": 0.026, "span": {"offset": 849, "length": 1}}, {"content": "Feedback", "polygon": [2047, 857, 2172, 858, 2171, 887], "confidence": 0.995, "span": {"offset": 851, "length": 8}}, {"content": "In", "polygon": [798, 958, 824, 826, 994, 800], "confidence": 0.993, "span": {"offset": 860, "length": 2}}, {"content": "this", "polygon": [834, 958, 898, 959, 899, 993, 835], "confidence": 0.989, "span": {"offset": 863, "length": 4}}, {"content": "article", "polygon": [905, 959, 1010, 958, 993, 906], "confidence": 0.996, "span": {"offset": 868, "length": 7}}, {"content": "Document", "polygon": [830, 1038, 957, 1070, 1068], "confidence": 0.993, "span": {"offset": 876, "length": 8}}, {"content": "layout", "polygon": [963, 1038, 1042, 1071], "confidence": 0.996, "span": {"offset": 885, "length": 6}}, {"content": "analysis", "polygon": [1048, 1038, 1148, 1149, 1070, 1071], "confidence": 0.996, "span": {"offset": 892, "length": 8}}, {"content": "Development", "polygon": [830, 1089, 995, 1090, 1123, 829, 1122], "confidence": 0.991, "span": {"offset": 901, "length": 11}}, {"content": "options", "polygon": [1001, 1090, 1098, 1099, 1124, 1123], "confidence": 0.996, "span": {"offset": 913, "length": 7}}, {"content": "Input", "polygon": [829, 1144, 893, 892, 1176], "confidence": 0.955, "span": {"offset": 921, "length": 5}}, {"content": "requirements", "polygon": [899, 1144, 1068, 1145, 1066, 1174, 1176], "confidence": 0.992, "span": {"offset": 927, "length": 12}}, {"content": "Form", "polygon": [829, 1194, 886, 1195, 885, 1227, 828], "confidence": 0.988, "span": {"offset": 940, "length": 4}}, {"content": "Recognizer", "polygon": [897, 1195, 1036, 1227, 896], "confidence": 0.994, "span": {"offset": 945, "length": 10}}, {"content": "Studio", "polygon": [1042, 1195, 1125, 1194, 1227], "confidence": 0.997, "span": {"offset": 956, "length": 6}}, {"content": "Show", "polygon": [831, 1258, 891, 890, 1287, 1288], "confidence": 0.979, "span": {"offset": 963, "length": 4}}, {"content": "4", "polygon": [905, 1258, 922, 921, 1288, 904, 1287], "confidence": 0.996, "span": {"offset": 968, "length": 1}}, {"content": "more", "polygon": [928, 1258, 998, 1259, 997, 1289, 1288], "confidence": 0.989, "span": {"offset": 970, "length": 4}}, {"content": "This", "polygon": [798, 1353, 854, 1354, 855, 1389, 799], "confidence": 0.987, "span": {"offset": 975, "length": 4}}, {"content": "article", "polygon": [861, 1354, 952, 1390, 862, 1389], "confidence": 0.996, "span": {"offset": 980, "length": 7}}, {"content": "applies", "polygon": [959, 1354, 1064, 1390], "confidence": 0.996, "span": {"offset": 988, "length": 7}}, {"content": "to:", "polygon": [1071, 1354, 1116, 1115, 1390], "confidence": 0.997, "span": {"offset": 996, "length": 3}}, {"content": "1", "polygon": [1157, 1350, 1171, 1354, 1160, 1376, 1146, 1369], "confidence": 0.595, "span": {"offset": 1000, "length": 1}}, {"content": "Form", "polygon": [1186, 1353, 1253, 1390, 1185], "confidence": 0.972, "span": {"offset": 1002, "length": 4}}, {"content": "Recognizer", "polygon": [1268, 1353, 1432, 1354, 1389, 1267, 1390], "confidence": 0.994, "span": {"offset": 1007, "length": 10}}, {"content": "v3.0.", "polygon": [1439, 1354, 1507, 1389], "confidence": 0.997, "span": {"offset": 1018, "length": 5}}, {"content": "Earlier", "polygon": [1514, 1354, 1606, 1389], "confidence": 0.996, "span": {"offset": 1024, "length": 7}}, {"content": "version:", "polygon": [1613, 1354, 1728, 1389], "confidence": 0.994, "span": {"offset": 1032, "length": 8}}, {"content": "Form", "polygon": [1735, 1354, 1802, 1389], "confidence": 0.989, "span": {"offset": 1041, "length": 4}}, {"content": "Recognizer", "polygon": [1817, 1354, 1974, 1389], "confidence": 0.994, "span": {"offset": 1046, "length": 10}}, {"content": "v2.1", "polygon": [1981, 1354, 2041, 1389], "confidence": 0.99, "span": {"offset": 1057, "length": 4}}, {"content": "Form", "polygon": [796, 1437, 861, 1473, 1472], "confidence": 0.988, "span": {"offset": 1062, "length": 4}}, {"content": "Recognizer", "polygon": [874, 1437, 1033, 1473], "confidence": 0.994, "span": {"offset": 1067, "length": 10}}, {"content": "layout", "polygon": [1040, 1437, 1128, 1473], "confidence": 0.995, "span": {"offset": 1078, "length": 6}}, {"content": "model", "polygon": [1135, 1437, 1228, 1473], "confidence": 0.997, "span": {"offset": 1085, "length": 5}}, {"content": "is", "polygon": [1235, 1437, 1259, 1473], "confidence": 0.997, "span": {"offset": 1091, "length": 2}}, {"content": "an", "polygon": [1266, 1437, 1301, 1473], "confidence": 0.997, "span": {"offset": 1094, "length": 2}}, {"content": "advanced", "polygon": [1309, 1437, 1444, 1473], "confidence": 0.995, "span": {"offset": 1097, "length": 8}}, {"content": "machine-learning", "polygon": [1451, 1437, 1700, 1473], "confidence": 0.993, "span": {"offset": 1106, "length": 16}}, {"content": "based", "polygon": [1708, 1437, 1793, 1473], "confidence": 0.997, "span": {"offset": 1123, "length": 5}}, {"content": "document", "polygon": [1800, 1437, 1945, 1946, 1472, 1801, 1473], "confidence": 0.995, "span": {"offset": 1129, "length": 8}}, {"content": "analysis", "polygon": [1952, 1437, 2064, 2065, 1472, 1953], "confidence": 0.995, "span": {"offset": 1138, "length": 8}}, {"content": "API", "polygon": [2071, 1437, 2122, 1472, 2072], "confidence": 0.88, "span": {"offset": 1147, "length": 3}}, {"content": "available", "polygon": [799, 1487, 918, 1523, 1522], "confidence": 0.994, "span": {"offset": 1151, "length": 9}}, {"content": "in", "polygon": [925, 1487, 953, 1486, 954, 1523], "confidence": 0.997, "span": {"offset": 1161, "length": 2}}, {"content": "the", "polygon": [961, 1486, 1006, 1523], "confidence": 0.997, "span": {"offset": 1164, "length": 3}}, {"content": "Form", "polygon": [1013, 1486, 1081, 1523], "confidence": 0.991, "span": {"offset": 1168, "length": 4}}, {"content": "Recognizer", "polygon": [1096, 1486, 1255, 1524, 1523], "confidence": 0.993, "span": {"offset": 1173, "length": 10}}, {"content": "cloud.", "polygon": [1263, 1486, 1348, 1524, 1262], "confidence": 0.994, "span": {"offset": 1184, "length": 6}}, {"content": "It", "polygon": [1355, 1486, 1377, 1376, 1524], "confidence": 0.912, "span": {"offset": 1191, "length": 2}}, {"content": "enables", "polygon": [1384, 1486, 1493, 1524, 1383], "confidence": 0.993, "span": {"offset": 1194, "length": 7}}, {"content": "you", "polygon": [1500, 1486, 1555, 1554, 1524], "confidence": 0.998, "span": {"offset": 1202, "length": 3}}, {"content": "to", "polygon": [1562, 1486, 1593, 1592, 1524], "confidence": 0.997, "span": {"offset": 1206, "length": 2}}, {"content": "take", "polygon": [1600, 1486, 1662, 1661, 1524], "confidence": 0.985, "span": {"offset": 1209, "length": 4}}, {"content": "documents", "polygon": [1669, 1486, 1828, 1487, 1827, 1523, 1668, 1524], "confidence": 0.993, "span": {"offset": 1214, "length": 9}}, {"content": "in", "polygon": [1836, 1487, 1864, 1863, 1523, 1835], "confidence": 0.997, "span": {"offset": 1224, "length": 2}}, {"content": "various", "polygon": [1871, 1487, 1973, 1972, 1522, 1870, 1523], "confidence": 0.994, "span": {"offset": 1227, "length": 7}}, {"content": "formats", "polygon": [1981, 1487, 2092, 1488, 2091, 1521, 1979, 1522], "confidence": 0.996, "span": {"offset": 1235, "length": 7}}, {"content": "and", "polygon": [2099, 1488, 2154, 2152, 1521, 2098], "confidence": 0.998, "span": {"offset": 1243, "length": 3}}, {"content": "return", "polygon": [795, 1540, 880, 881, 1574, 796], "confidence": 0.991, "span": {"offset": 1247, "length": 6}}, {"content": "structured", "polygon": [887, 1539, 1033, 1574, 888], "confidence": 0.993, "span": {"offset": 1254, "length": 10}}, {"content": "data", "polygon": [1040, 1539, 1105, 1106, 1574, 1041], "confidence": 0.991, "span": {"offset": 1265, "length": 4}}, {"content": "representations", "polygon": [1112, 1539, 1333, 1538, 1575, 1113, 1574], "confidence": 0.991, "span": {"offset": 1270, "length": 15}}, {"content": "of", "polygon": [1340, 1538, 1370, 1575], "confidence": 0.997, "span": {"offset": 1286, "length": 2}}, {"content": "the", "polygon": [1377, 1538, 1426, 1575], "confidence": 0.997, "span": {"offset": 1289, "length": 3}}, {"content": "documents.", "polygon": [1433, 1538, 1598, 1597, 1575], "confidence": 0.992, "span": {"offset": 1293, "length": 10}}, {"content": "It", "polygon": [1605, 1538, 1628, 1574, 1604], "confidence": 0.855, "span": {"offset": 1304, "length": 2}}, {"content": "combines", "polygon": [1635, 1538, 1772, 1771, 1574, 1634], "confidence": 0.993, "span": {"offset": 1307, "length": 8}}, {"content": "an", "polygon": [1779, 1538, 1815, 1574, 1778], "confidence": 0.997, "span": {"offset": 1316, "length": 2}}, {"content": "enhanced", "polygon": [1823, 1538, 1961, 1574, 1822], "confidence": 0.995, "span": {"offset": 1319, "length": 8}}, {"content": "version", "polygon": [1969, 1538, 2071, 1539, 2070, 1573, 1968, 1574], "confidence": 0.996, "span": {"offset": 1328, "length": 7}}, {"content": "of", "polygon": [2078, 1539, 2111, 2110, 1573, 2077], "confidence": 0.997, "span": {"offset": 1336, "length": 2}}, {"content": "our", "polygon": [2118, 1539, 2169, 2168, 1573, 2117], "confidence": 0.997, "span": {"offset": 1339, "length": 3}}, {"content": "powerful", "polygon": [796, 1589, 920, 1588, 1627, 1626], "confidence": 0.993, "span": {"offset": 1343, "length": 8}}, {"content": "Optical", "polygon": [928, 1588, 1028, 1627], "confidence": 0.995, "span": {"offset": 1352, "length": 7}}, {"content": "Character", "polygon": [1035, 1588, 1173, 1628, 1036, 1627], "confidence": 0.994, "span": {"offset": 1360, "length": 9}}, {"content": "Recognition", "polygon": [1180, 1588, 1350, 1351, 1628, 1181], "confidence": 0.993, "span": {"offset": 1370, "length": 11}}, {"content": "(OCR)", "polygon": [1358, 1588, 1441, 1628], "confidence": 0.996, "span": {"offset": 1382, "length": 5}}, {"content": "capabilities", "polygon": [1448, 1588, 1608, 1628], "confidence": 0.991, "span": {"offset": 1388, "length": 12}}, {"content": "with", "polygon": [1616, 1588, 1676, 1628], "confidence": 0.988, "span": {"offset": 1401, "length": 4}}, {"content": "deep", "polygon": [1683, 1588, 1756, 1589, 1627, 1628], "confidence": 0.987, "span": {"offset": 1406, "length": 4}}, {"content": "learning", "polygon": [1763, 1589, 1879, 1627, 1764], "confidence": 0.995, "span": {"offset": 1411, "length": 8}}, {"content": "models", "polygon": [1886, 1589, 1991, 1590, 1626, 1627], "confidence": 0.997, "span": {"offset": 1420, "length": 6}}, {"content": "to", "polygon": [1999, 1590, 2031, 1626], "confidence": 0.997, "span": {"offset": 1427, "length": 2}}, {"content": "extract", "polygon": [2039, 1590, 2139, 1591, 1625, 1626], "confidence": 0.996, "span": {"offset": 1430, "length": 7}}, {"content": "text,", "polygon": [797, 1642, 856, 855, 1676, 796, 1675], "confidence": 0.994, "span": {"offset": 1438, "length": 5}}, {"content": "tables,", "polygon": [863, 1642, 955, 1677, 862, 1676], "confidence": 0.996, "span": {"offset": 1444, "length": 7}}, {"content": "selection", "polygon": [962, 1642, 1089, 1088, 1678, 961, 1677], "confidence": 0.995, "span": {"offset": 1452, "length": 9}}, {"content": "marks,", "polygon": [1096, 1642, 1191, 1678, 1095], "confidence": 0.997, "span": {"offset": 1462, "length": 6}}, {"content": "and", "polygon": [1198, 1642, 1252, 1251, 1678, 1197], "confidence": 0.998, "span": {"offset": 1469, "length": 3}}, {"content": "document", "polygon": [1259, 1642, 1407, 1643, 1406, 1677, 1678], "confidence": 0.996, "span": {"offset": 1473, "length": 8}}, {"content": "structure.", "polygon": [1413, 1643, 1548, 1644, 1547, 1676, 1677], "confidence": 0.992, "span": {"offset": 1482, "length": 10}}, {"content": "Document", "polygon": [795, 1768, 1116, 1764, 1118, 1834, 797, 1821], "confidence": 0.994, "span": {"offset": 1493, "length": 8}}, {"content": "layout", "polygon": [1130, 1764, 1331, 1763, 1333, 1837, 1131, 1835], "confidence": 0.997, "span": {"offset": 1502, "length": 6}}, {"content": "analysis", "polygon": [1344, 1763, 1591, 1594, 1835, 1346, 1837], "confidence": 0.996, "span": {"offset": 1509, "length": 8}}, {"content": "Document", "polygon": [797, 1879, 943, 1878, 944, 1910, 798, 1908], "confidence": 0.992, "span": {"offset": 1518, "length": 8}}, {"content": "structure", "polygon": [950, 1878, 1077, 1078, 1912, 951, 1910], "confidence": 0.994, "span": {"offset": 1527, "length": 9}}, {"content": "layout", "polygon": [1084, 1878, 1174, 1175, 1912, 1085], "confidence": 0.996, "span": {"offset": 1537, "length": 6}}, {"content": "analysis", "polygon": [1181, 1878, 1290, 1291, 1913], "confidence": 0.995, "span": {"offset": 1544, "length": 8}}, {"content": "is", "polygon": [1297, 1877, 1321, 1322, 1913], "confidence": 0.997, "span": {"offset": 1553, "length": 2}}, {"content": "the", "polygon": [1328, 1877, 1376, 1914, 1913], "confidence": 0.997, "span": {"offset": 1556, "length": 3}}, {"content": "process", "polygon": [1383, 1877, 1492, 1493, 1914], "confidence": 0.996, "span": {"offset": 1560, "length": 7}}, {"content": "of", "polygon": [1499, 1877, 1530, 1914], "confidence": 0.997, "span": {"offset": 1568, "length": 2}}, {"content": "analyzing", "polygon": [1536, 1877, 1670, 1878, 1914, 1537], "confidence": 0.994, "span": {"offset": 1571, "length": 9}}, {"content": "a", "polygon": [1679, 1878, 1696, 1697, 1914], "confidence": 0.995, "span": {"offset": 1581, "length": 1}}, {"content": "document", "polygon": [1703, 1878, 1850, 1913, 1914], "confidence": 0.995, "span": {"offset": 1583, "length": 8}}, {"content": "to", "polygon": [1857, 1878, 1887, 1913], "confidence": 0.997, "span": {"offset": 1592, "length": 2}}, {"content": "extract", "polygon": [1894, 1878, 1991, 1879, 1912, 1913], "confidence": 0.996, "span": {"offset": 1595, "length": 7}}, {"content": "regions", "polygon": [1997, 1879, 2105, 1910, 1912], "confidence": 0.996, "span": {"offset": 1603, "length": 7}}, {"content": "of", "polygon": [2111, 1880, 2147, 1910, 2112], "confidence": 0.996, "span": {"offset": 1611, "length": 2}}, {"content": "interact", "polygon": [798, 1931, 905, 1930, 1949], "confidence": 0.41, "span": {"offset": 1614, "length": 8}}, {"content": "and", "polygon": [916, 1930, 964, 1950, 1949], "confidence": 0.988, "span": {"offset": 1623, "length": 3}}, {"content": "their", "polygon": [975, 1930, 1041, 1929, 1950], "confidence": 0.209, "span": {"offset": 1627, "length": 5}}, {"content": "intAr", "polygon": [1047, 1929, 1116, 1950], "confidence": 0.21, "span": {"offset": 1633, "length": 5}}, {"content": "malatiAnchine", "polygon": [1127, 1929, 1306, 1928, 1950], "confidence": 0.635, "span": {"offset": 1639, "length": 13}}, {"content": "The", "polygon": [1325, 1928, 1372, 1373, 1951, 1950], "confidence": 0.6, "span": {"offset": 1653, "length": 3}}, {"content": "Anal", "polygon": [1386, 1928, 1444, 1951], "confidence": 0.874, "span": {"offset": 1657, "length": 4}}, {"content": "is", "polygon": [1448, 1928, 1474, 1951], "confidence": 0.512, "span": {"offset": 1662, "length": 2}}, {"content": "to", "polygon": [1482, 1928, 1511, 1512, 1951, 1483], "confidence": 0.294, "span": {"offset": 1665, "length": 2}}, {"content": "Avtract", "polygon": [1525, 1928, 1618, 1929, 1619, 1951], "confidence": 0.395, "span": {"offset": 1668, "length": 7}}, {"content": "tout", "polygon": [1624, 1929, 1680, 1951], "confidence": 0.361, "span": {"offset": 1676, "length": 4}}, {"content": "and", "polygon": [1691, 1929, 1738, 1739, 1951], "confidence": 0.953, "span": {"offset": 1681, "length": 3}}, {"content": "structural", "polygon": [1749, 1929, 1885, 1930, 1886, 1950, 1750, 1951], "confidence": 0.198, "span": {"offset": 1685, "length": 10}}, {"content": "AlAmante", "polygon": [1894, 1930, 2019, 1931, 2020, 1950], "confidence": 0.85, "span": {"offset": 1696, "length": 8}}, {"content": "from", "polygon": [2027, 1931, 2088, 2089, 1950, 2028], "confidence": 0.613, "span": {"offset": 1705, "length": 4}}, {"content": "the", "polygon": [2102, 1932, 2150, 2151, 1950, 2103], "confidence": 0.593, "span": {"offset": 1710, "length": 3}}, {"content": "El", "polygon": [77, 1850, 97, 1877], "confidence": 0.217, "span": {"offset": 1714, "length": 2}}, {"content": "Download", "polygon": [102, 1850, 235, 1879, 103, 1877], "confidence": 0.995, "span": {"offset": 1717, "length": 8}}, {"content": "PDF", "polygon": [241, 1850, 295, 1849, 294, 1879], "confidence": 0.997, "span": {"offset": 1726, "length": 3}}], "selectionMarks": [{"state": "unselected", "polygon": [114, 1131, 146, 1131, 146, 1162, 114, 1162], "confidence": 0.853, "span": {"offset": 1730, "length": 12}}, {"state": "unselected", "polygon": [114, 1194, 147, 1194, 147, 1223, 114, 1223], "confidence": 0.658, "span": {"offset": 1743, "length": 12}}, {"state": "unselected", "polygon": [113, 1250, 147, 1250, 147, 1282, 113, 1282], "confidence": 0.45, "span": {"offset": 1756, "length": 12}}, {"state": "selected", "polygon": [1140, 1346, 1176, 1346, 1176, 1383, 1140, 1383], "confidence": 0.2, "span": {"offset": 1769, "length": 10}}], "lines": [{"content": "Arc File", "polygon": [104, 22, 250, 22, 251, 48, 104, 49], "spans": [{"offset": 0, "length": 8}]}, {"content": "Edit View", "polygon": [265, 21, 449, 22, 449, 52, 265, 51], "spans": [{"offset": 9, "length": 9}]}, {"content": "Spaces", "polygon": [456, 23, 559, 23, 559, 52, 456, 51], "spans": [{"offset": 19, "length": 6}]}, {"content": "Tabs", "polygon": [580, 22, 661, 22, 660, 50, 581, 50], "spans": [{"offset": 26, "length": 4}]}, {"content": "Archive", "polygon": [683, 23, 790, 23, 790, 49, 683, 50], "spans": [{"offset": 31, "length": 7}]}, {"content": "Extensions", "polygon": [819, 24, 963, 24, 963, 50, 819, 49], "spans": [{"offset": 39, "length": 10}]}, {"content": "Window", "polygon": [991, 22, 1097, 23, 1097, 50, 991, 49], "spans": [{"offset": 50, "length": 6}]}, {"content": "Help", "polygon": [1125, 24, 1191, 25, 1190, 52, 1125, 50], "spans": [{"offset": 57, "length": 4}]}, {"content": "US", "polygon": [2293, 24, 2330, 24, 2330, 47, 2293, 46], "spans": [{"offset": 62, "length": 2}]}, {"content": "Thu Apr 13 11:11 AM", "polygon": [2718, 21, 2996, 21, 2996, 50, 2718, 50], "spans": [{"offset": 65, "length": 19}]}, {"content": "Register now >", "polygon": [738, 207, 962, 206, 962, 240, 738, 242], "spans": [{"offset": 85, "length": 14}]}, {"content": "Portal", "polygon": [2614, 517, 2698, 518, 2698, 546, 2613, 545], "spans": [{"offset": 100, "length": 6}]}, {"content": "Microsoft Build", "polygon": [52, 151, 522, 150, 522, 212, 52, 213], "spans": [{"offset": 107, "length": 15}]}, {"content": "May 23-25, 2023", "polygon": [51, 261, 257, 260, 258, 292, 51, 293], "spans": [{"offset": 123, "length": 15}]}, {"content": "Microsoft", "polygon": [108, 405, 271, 404, 272, 440, 109, 442], "spans": [{"offset": 139, "length": 9}]}, {"content": "Learn", "polygon": [366, 410, 459, 411, 459, 441, 366, 440], "spans": [{"offset": 149, "length": 5}]}, {"content": "Documentation", "polygon": [503, 412, 710, 412, 710, 440, 503, 439], "spans": [{"offset": 155, "length": 13}]}, {"content": "...", "polygon": [3019, 108, 3017, 138, 3006, 137, 3008, 106], "spans": [{"offset": 169, "length": 3}]}, {"content": "\u00d7", "polygon": [2887, 130, 2916, 131, 2916, 159, 2887, 157], "spans": [{"offset": 173, "length": 1}]}, {"content": "Training Certifications Q&A Code Samples Assessments", "polygon": [719, 410, 1542, 410, 1542, 441, 719, 441], "spans": [{"offset": 175, "length": 52}]}, {"content": "Shows", "polygon": [1549, 411, 1638, 412, 1637, 439, 1549, 438], "spans": [{"offset": 228, "length": 5}]}, {"content": "Events", "polygon": [1658, 411, 1746, 413, 1746, 439, 1658, 437], "spans": [{"offset": 234, "length": 6}]}, {"content": "Search", "polygon": [2416, 406, 2546, 408, 2546, 439, 2415, 437], "spans": [{"offset": 241, "length": 6}]}, {"content": "Sign in", "polygon": [2831, 409, 2920, 411, 2920, 439, 2831, 439], "spans": [{"offset": 248, "length": 7}]}, {"content": "Azure Product documentation v Architecture v Learn Azure v Develop v Resources v", "polygon": [67, 518, 1299, 518, 1299, 550, 67, 550], "spans": [{"offset": 256, "length": 80}]}, {"content": "Version", "polygon": [50, 648, 161, 648, 161, 678, 50, 677], "spans": [{"offset": 337, "length": 7}]}, {"content": "Form Recognizer v3.0", "polygon": [71, 714, 348, 713, 348, 758, 71, 759], "spans": [{"offset": 345, "length": 20}]}, {"content": "V", "polygon": [656, 722, 679, 723, 678, 741, 655, 740], "spans": [{"offset": 366, "length": 1}]}, {"content": "Filter by title", "polygon": [68, 797, 271, 800, 270, 832, 68, 829], "spans": [{"offset": 368, "length": 15}]}, {"content": "Free account", "polygon": [2752, 518, 2919, 518, 2919, 547, 2752, 547], "spans": [{"offset": 384, "length": 12}]}, {"content": "Learn / Azure / Applied Al Services / Form Recognizer /", "polygon": [793, 656, 1529, 657, 1529, 691, 793, 690], "spans": [{"offset": 397, "length": 55}]}, {"content": "+", "polygon": [2009, 661, 2029, 660, 2029, 680, 2009, 681], "spans": [{"offset": 453, "length": 1}]}, {"content": "...", "polygon": [2165, 657, 2165, 682, 2152, 682, 2153, 657], "spans": [{"offset": 455, "length": 3}]}, {"content": "Azure Form Recognizer layout model", "polygon": [797, 740, 2141, 740, 2141, 826, 797, 823], "spans": [{"offset": 459, "length": 34}]}, {"content": "Analyze document API response", "polygon": [115, 898, 515, 899, 515, 930, 115, 930], "spans": [{"offset": 494, "length": 29}]}, {"content": "Read OCR model", "polygon": [114, 957, 324, 957, 324, 986, 114, 986], "spans": [{"offset": 524, "length": 14}]}, {"content": "General document model", "polygon": [116, 1016, 430, 1016, 430, 1046, 116, 1046], "spans": [{"offset": 539, "length": 22}]}, {"content": "Layout model", "polygon": [113, 1076, 293, 1074, 293, 1106, 113, 1107], "spans": [{"offset": 562, "length": 12}]}, {"content": "NEW", "polygon": [119, 1141, 143, 1141, 142, 1155, 118, 1154], "spans": [{"offset": 575, "length": 3}]}, {"content": "Query field extraction (preview)", "polygon": [151, 1133, 539, 1133, 539, 1166, 151, 1167], "spans": [{"offset": 579, "length": 32}]}, {"content": "NEW", "polygon": [121, 1199, 143, 1200, 142, 1213, 121, 1212], "spans": [{"offset": 612, "length": 3}]}, {"content": "Health insurance card model", "polygon": [148, 1193, 508, 1193, 508, 1225, 148, 1225], "spans": [{"offset": 616, "length": 27}]}, {"content": "NEW", "polygon": [117, 1259, 140, 1260, 140, 1273, 117, 1272], "spans": [{"offset": 644, "length": 3}]}, {"content": "Add-on capabilities (preview)", "polygon": [151, 1252, 511, 1252, 511, 1285, 151, 1285], "spans": [{"offset": 648, "length": 29}]}, {"content": "W-2 form model", "polygon": [115, 1312, 322, 1312, 322, 1342, 115, 1341], "spans": [{"offset": 678, "length": 14}]}, {"content": "Invoice model", "polygon": [116, 1373, 291, 1373, 292, 1400, 116, 1400], "spans": [{"offset": 693, "length": 13}]}, {"content": "Receipt model", "polygon": [117, 1431, 294, 1431, 294, 1461, 117, 1461], "spans": [{"offset": 707, "length": 13}]}, {"content": "ID document model", "polygon": [115, 1489, 364, 1490, 364, 1519, 115, 1518], "spans": [{"offset": 721, "length": 17}]}, {"content": "Business card model", "polygon": [117, 1550, 366, 1549, 366, 1578, 117, 1578], "spans": [{"offset": 739, "length": 19}]}, {"content": "> Custom models", "polygon": [89, 1607, 310, 1608, 310, 1638, 89, 1636], "spans": [{"offset": 759, "length": 15}]}, {"content": "> Tutorials", "polygon": [55, 1668, 188, 1669, 188, 1696, 55, 1694], "spans": [{"offset": 775, "length": 11}]}, {"content": "> Reference", "polygon": [56, 1728, 207, 1729, 206, 1755, 56, 1753], "spans": [{"offset": 787, "length": 11}]}, {"content": "> Resources", "polygon": [56, 1787, 210, 1789, 209, 1814, 56, 1811], "spans": [{"offset": 799, "length": 11}]}, {"content": "Article \u00b7 03/12/2023 \u00b7 9 contributors", "polygon": [795, 857, 1258, 857, 1258, 890, 795, 889], "spans": [{"offset": 811, "length": 37}]}, {"content": "& Feedback", "polygon": [2019, 857, 2174, 857, 2174, 886, 2019, 886], "spans": [{"offset": 849, "length": 10}]}, {"content": "In this article", "polygon": [797, 957, 1013, 957, 1013, 992, 797, 993], "spans": [{"offset": 860, "length": 15}]}, {"content": "Document layout analysis", "polygon": [829, 1037, 1148, 1037, 1148, 1070, 829, 1069], "spans": [{"offset": 876, "length": 24}]}, {"content": "Development options", "polygon": [829, 1088, 1100, 1090, 1100, 1123, 829, 1121], "spans": [{"offset": 901, "length": 19}]}, {"content": "Input requirements", "polygon": [829, 1143, 1068, 1143, 1068, 1174, 829, 1175], "spans": [{"offset": 921, "length": 18}]}, {"content": "Form Recognizer Studio", "polygon": [827, 1193, 1126, 1193, 1126, 1226, 827, 1226], "spans": [{"offset": 940, "length": 22}]}, {"content": "Show 4 more", "polygon": [831, 1257, 1001, 1258, 1001, 1288, 831, 1287], "spans": [{"offset": 963, "length": 11}]}, {"content": "This article applies to:", "polygon": [796, 1353, 1117, 1353, 1117, 1389, 796, 1388], "spans": [{"offset": 975, "length": 24}]}, {"content": "1", "polygon": [1160, 1350, 1172, 1356, 1158, 1375, 1146, 1369], "spans": [{"offset": 1000, "length": 1}]}, {"content": "Form Recognizer v3.0. Earlier version: Form Recognizer v2.1", "polygon": [1183, 1353, 2040, 1353, 2040, 1389, 1183, 1389], "spans": [{"offset": 1002, "length": 59}]}, {"content": "Form Recognizer layout model is an advanced machine-learning based document analysis API", "polygon": [795, 1436, 2123, 1436, 2123, 1472, 795, 1472], "spans": [{"offset": 1062, "length": 88}]}, {"content": "available in the Form Recognizer cloud. It enables you to take documents in various formats and", "polygon": [797, 1485, 2156, 1485, 2156, 1523, 797, 1523], "spans": [{"offset": 1151, "length": 95}]}, {"content": "return structured data representations of the documents. It combines an enhanced version of our", "polygon": [794, 1538, 2170, 1537, 2170, 1573, 794, 1574], "spans": [{"offset": 1247, "length": 95}]}, {"content": "powerful Optical Character Recognition (OCR) capabilities with deep learning models to extract", "polygon": [795, 1587, 2139, 1588, 2139, 1627, 795, 1627], "spans": [{"offset": 1343, "length": 94}]}, {"content": "text, tables, selection marks, and document structure.", "polygon": [796, 1641, 1547, 1642, 1547, 1678, 796, 1676], "spans": [{"offset": 1438, "length": 54}]}, {"content": "Document layout analysis", "polygon": [795, 1762, 1593, 1762, 1593, 1837, 795, 1833], "spans": [{"offset": 1493, "length": 24}]}, {"content": "Document structure layout analysis is the process of analyzing a document to extract regions of", "polygon": [796, 1877, 2147, 1878, 2147, 1913, 796, 1912], "spans": [{"offset": 1518, "length": 95}]}, {"content": "interact and their intAr malatiAnchine The Anal is to Avtract tout and structural AlAmante from the", "polygon": [798, 1928, 2150, 1928, 2150, 1950, 798, 1949], "spans": [{"offset": 1614, "length": 99}]}, {"content": "El Download PDF", "polygon": [76, 1848, 298, 1848, 298, 1879, 76, 1878], "spans": [{"offset": 1714, "length": 15}]}], "spans": [{"offset": 0, "length": 1779}], "kind": "document"}], "tables": [], "paragraphs": [{"spans": [{"offset": 0, "length": 8}], "boundingRegions": [{"polygon": [104, 22, 251, 22, 251, 49, 104, 49]}], "role": "pageHeader", "content": "Arc File"}, {"spans": [{"offset": 9, "length": 9}], "boundingRegions": [{"polygon": [265, 21, 449, 22, 449, 52, 265, 51]}], "role": "pageHeader", "content": "Edit View"}, {"spans": [{"offset": 19, "length": 6}], "boundingRegions": [{"polygon": [456, 23, 559, 23, 559, 52, 456, 52]}], "role": "pageHeader", "content": "Spaces"}, {"spans": [{"offset": 26, "length": 4}], "boundingRegions": [{"polygon": [580, 22, 661, 22, 661, 50, 580, 50]}], "role": "pageHeader", "content": "Tabs"}, {"spans": [{"offset": 31, "length": 18}], "boundingRegions": [{"polygon": [683, 23, 963, 23, 963, 50, 683, 50]}], "role": "pageHeader", "content": "Archive Extensions"}, {"spans": [{"offset": 50, "length": 6}], "boundingRegions": [{"polygon": [991, 22, 1097, 23, 1097, 50, 991, 49]}], "role": "pageHeader", "content": "Window"}, {"spans": [{"offset": 57, "length": 4}], "boundingRegions": [{"polygon": [1125, 24, 1191, 25, 1191, 52, 1125, 51]}], "role": "pageNumber", "content": "Help"}, {"spans": [{"offset": 62, "length": 2}], "boundingRegions": [{"polygon": [2293, 24, 2330, 24, 2330, 47, 2293, 47]}], "role": "pageHeader", "content": "US"}, {"spans": [{"offset": 65, "length": 19}], "boundingRegions": [{"polygon": [2718, 21, 2996, 21, 2996, 50, 2718, 50]}], "role": "pageHeader", "content": "Thu Apr 13 11:11 AM"}, {"spans": [{"offset": 85, "length": 14}], "boundingRegions": [{"polygon": [738, 207, 962, 206, 962, 241, 738, 242]}], "role": "pageHeader", "content": "Register now >"}, {"spans": [{"offset": 100, "length": 6}], "boundingRegions": [{"polygon": [2613, 517, 2698, 518, 2698, 546, 2613, 545]}], "role": "pageHeader", "content": "Portal"}, {"spans": [{"offset": 107, "length": 15}], "boundingRegions": [{"polygon": [52, 151, 522, 150, 522, 212, 52, 213]}], "role": "title", "content": "Microsoft Build"}, {"spans": [{"offset": 123, "length": 15}], "boundingRegions": [{"polygon": [51, 261, 258, 260, 258, 292, 51, 293]}], "content": "May 23-25, 2023"}, {"spans": [{"offset": 139, "length": 9}], "boundingRegions": [{"polygon": [108, 405, 272, 403, 272, 440, 108, 442]}], "content": "Microsoft"}, {"spans": [{"offset": 149, "length": 5}], "boundingRegions": [{"polygon": [366, 410, 459, 411, 459, 441, 366, 440]}], "content": "Learn"}, {"spans": [{"offset": 155, "length": 13}], "boundingRegions": [{"polygon": [503, 412, 710, 412, 710, 440, 503, 440]}], "content": "Documentation"}, {"spans": [{"offset": 169, "length": 3}], "boundingRegions": [{"polygon": [3008, 106, 3019, 107, 3017, 138, 3006, 137]}], "content": "..."}, {"spans": [{"offset": 173, "length": 1}], "boundingRegions": [{"polygon": [2887, 130, 2917, 131, 2916, 159, 2886, 158]}], "content": "\u00d7"}, {"spans": [{"offset": 175, "length": 52}], "boundingRegions": [{"polygon": [719, 410, 1542, 410, 1542, 441, 719, 441]}], "content": "Training Certifications Q&A Code Samples Assessments"}, {"spans": [{"offset": 228, "length": 5}], "boundingRegions": [{"polygon": [1549, 411, 1638, 412, 1638, 439, 1549, 438]}], "content": "Shows"}, {"spans": [{"offset": 234, "length": 6}], "boundingRegions": [{"polygon": [1658, 411, 1747, 413, 1746, 439, 1657, 437]}], "content": "Events"}, {"spans": [{"offset": 241, "length": 6}], "boundingRegions": [{"polygon": [2415, 406, 2546, 408, 2546, 439, 2415, 437]}], "content": "Search"}, {"spans": [{"offset": 248, "length": 7}], "boundingRegions": [{"polygon": [2831, 409, 2920, 409, 2920, 439, 2831, 439]}], "content": "Sign in"}, {"spans": [{"offset": 256, "length": 80}], "boundingRegions": [{"polygon": [67, 518, 1299, 518, 1299, 550, 67, 550]}], "content": "Azure Product documentation v Architecture v Learn Azure v Develop v Resources v"}, {"spans": [{"offset": 337, "length": 7}], "boundingRegions": [{"polygon": [50, 648, 161, 648, 161, 678, 50, 678]}], "content": "Version"}, {"spans": [{"offset": 345, "length": 22}], "boundingRegions": [{"polygon": [71, 714, 679, 712, 679, 757, 71, 759]}], "content": "Form Recognizer v3.0 V"}, {"spans": [{"offset": 368, "length": 15}], "boundingRegions": [{"polygon": [68, 797, 271, 800, 271, 832, 68, 829]}], "content": "Filter by title"}, {"spans": [{"offset": 384, "length": 12}], "boundingRegions": [{"polygon": [2752, 518, 2919, 518, 2919, 547, 2752, 547]}], "content": "Free account"}, {"spans": [{"offset": 397, "length": 55}], "boundingRegions": [{"polygon": [793, 656, 1529, 657, 1529, 691, 793, 690]}], "content": "Learn / Azure / Applied Al Services / Form Recognizer /"}, {"spans": [{"offset": 453, "length": 5}], "boundingRegions": [{"polygon": [2009, 657, 2165, 657, 2165, 682, 2009, 682]}], "content": "+ ..."}, {"spans": [{"offset": 459, "length": 34}], "boundingRegions": [{"polygon": [797, 740, 2141, 740, 2141, 826, 797, 826]}], "role": "sectionHeading", "content": "Azure Form Recognizer layout model"}, {"spans": [{"offset": 494, "length": 44}], "boundingRegions": [{"polygon": [114, 898, 515, 899, 515, 987, 114, 986]}], "content": "Analyze document API response Read OCR model"}, {"spans": [{"offset": 539, "length": 22}], "boundingRegions": [{"polygon": [116, 1016, 430, 1016, 430, 1046, 116, 1046]}], "content": "General document model"}, {"spans": [{"offset": 562, "length": 12}], "boundingRegions": [{"polygon": [113, 1075, 293, 1074, 293, 1106, 113, 1107]}], "content": "Layout model"}, {"spans": [{"offset": 575, "length": 36}], "boundingRegions": [{"polygon": [118, 1133, 539, 1133, 539, 1167, 118, 1167]}], "content": "NEW Query field extraction (preview)"}, {"spans": [{"offset": 612, "length": 31}], "boundingRegions": [{"polygon": [121, 1193, 508, 1193, 508, 1225, 121, 1225]}], "content": "NEW Health insurance card model"}, {"spans": [{"offset": 644, "length": 33}], "boundingRegions": [{"polygon": [117, 1252, 511, 1252, 511, 1285, 117, 1285]}], "content": "NEW Add-on capabilities (preview)"}, {"spans": [{"offset": 678, "length": 14}], "boundingRegions": [{"polygon": [115, 1312, 322, 1312, 322, 1342, 115, 1342]}], "content": "W-2 form model"}, {"spans": [{"offset": 693, "length": 13}], "boundingRegions": [{"polygon": [116, 1373, 292, 1373, 292, 1400, 116, 1400]}], "content": "Invoice model"}, {"spans": [{"offset": 707, "length": 13}], "boundingRegions": [{"polygon": [117, 1431, 294, 1431, 294, 1461, 117, 1461]}], "content": "Receipt model"}, {"spans": [{"offset": 721, "length": 17}], "boundingRegions": [{"polygon": [115, 1489, 364, 1490, 364, 1519, 115, 1518]}], "content": "ID document model"}, {"spans": [{"offset": 739, "length": 19}], "boundingRegions": [{"polygon": [117, 1549, 366, 1549, 366, 1578, 117, 1578]}], "content": "Business card model"}, {"spans": [{"offset": 759, "length": 15}], "boundingRegions": [{"polygon": [89, 1607, 310, 1608, 310, 1638, 89, 1637]}], "content": "> Custom models"}, {"spans": [{"offset": 775, "length": 11}], "boundingRegions": [{"polygon": [55, 1668, 188, 1669, 188, 1696, 55, 1695]}], "content": "> Tutorials"}, {"spans": [{"offset": 787, "length": 11}], "boundingRegions": [{"polygon": [56, 1728, 207, 1729, 207, 1755, 56, 1754]}], "content": "> Reference"}, {"spans": [{"offset": 799, "length": 11}], "boundingRegions": [{"polygon": [56, 1787, 210, 1789, 210, 1814, 56, 1812]}], "content": "> Resources"}, {"spans": [{"offset": 811, "length": 37}], "boundingRegions": [{"polygon": [795, 857, 1258, 857, 1258, 890, 795, 890]}], "content": "Article \u00b7 03/12/2023 \u00b7 9 contributors"}, {"spans": [{"offset": 849, "length": 10}], "boundingRegions": [{"polygon": [2019, 857, 2174, 857, 2174, 886, 2019, 886]}], "content": "& Feedback"}, {"spans": [{"offset": 860, "length": 15}], "boundingRegions": [{"polygon": [797, 957, 1013, 957, 1013, 993, 797, 993]}], "content": "In this article"}, {"spans": [{"offset": 876, "length": 24}], "boundingRegions": [{"polygon": [829, 1037, 1148, 1037, 1148, 1070, 829, 1070]}], "content": "Document layout analysis"}, {"spans": [{"offset": 901, "length": 19}], "boundingRegions": [{"polygon": [829, 1088, 1100, 1090, 1100, 1123, 829, 1121]}], "content": "Development options"}, {"spans": [{"offset": 921, "length": 18}], "boundingRegions": [{"polygon": [829, 1143, 1068, 1143, 1068, 1175, 829, 1175]}], "content": "Input requirements"}, {"spans": [{"offset": 940, "length": 22}], "boundingRegions": [{"polygon": [827, 1193, 1126, 1193, 1126, 1226, 827, 1226]}], "content": "Form Recognizer Studio"}, {"spans": [{"offset": 963, "length": 11}], "boundingRegions": [{"polygon": [831, 1257, 1001, 1258, 1001, 1288, 831, 1287]}], "content": "Show 4 more"}, {"spans": [{"offset": 975, "length": 86}], "boundingRegions": [{"polygon": [796, 1350, 2040, 1350, 2040, 1389, 796, 1389]}], "content": "This article applies to: 1 Form Recognizer v3.0. Earlier version: Form Recognizer v2.1"}, {"spans": [{"offset": 1062, "length": 430}], "boundingRegions": [{"polygon": [794, 1436, 2170, 1436, 2170, 1678, 794, 1678]}], "content": "Form Recognizer layout model is an advanced machine-learning based document analysis API available in the Form Recognizer cloud. It enables you to take documents in various formats and return structured data representations of the documents. It combines an enhanced version of our powerful Optical Character Recognition (OCR) capabilities with deep learning models to extract text, tables, selection marks, and document structure."}, {"spans": [{"offset": 1493, "length": 24}], "boundingRegions": [{"polygon": [795, 1762, 1593, 1762, 1593, 1837, 795, 1837]}], "role": "sectionHeading", "content": "Document layout analysis"}, {"spans": [{"offset": 1518, "length": 195}], "boundingRegions": [{"polygon": [796, 1877, 2150, 1878, 2150, 1950, 796, 1949]}], "content": "Document structure layout analysis is the process of analyzing a document to extract regions of interact and their intAr malatiAnchine The Anal is to Avtract tout and structural AlAmante from the"}, {"spans": [{"offset": 1714, "length": 15}], "boundingRegions": [{"polygon": [76, 1848, 298, 1848, 298, 1879, 76, 1879]}], "role": "pageFooter", "content": "El Download PDF"}], "styles": [{"confidence": 0.8, "spans": [{"offset": 366, "length": 1}], "isHandwritten": true}, {"confidence": 0.7, "spans": [{"offset": 453, "length": 1}, {"offset": 1000, "length": 1}], "isHandwritten": true}]}}